guiprint/__init__.py
guiprint/cli.py
guiprint/guiprint_core.py
guiprint-1.0.5.dist-info/AUTHORS.rst
guiprint-1.0.5.dist-info/LICENSE
guiprint-1.0.5.dist-info/METADATA
guiprint-1.0.5.dist-info/WHEEL
guiprint-1.0.5.dist-info/entry_points.txt
guiprint-1.0.5.dist-info/top_level.txt
guiprint-1.0.5.dist-info/RECORD
