Metadata-Version: 2.1
Name: guiprint
Version: 1.0.5
Summary: Magically turn your CLI into a GUI program and make it more user friendly.
Home-page: https://github.com/ashrafulislambd/guiprint
Author: Md Ashraful Islam
Author-email: imdashraful17@gmail.com
License: MIT license
Keywords: guiprint
Classifier: Development Status :: 2 - Pre-Alpha
Classifier: Intended Audience :: Developers
Classifier: License :: OSI Approved :: MIT License
Classifier: Natural Language :: English
Classifier: Programming Language :: Python :: 3
Classifier: Programming Language :: Python :: 3.6
Classifier: Programming Language :: Python :: 3.7
Classifier: Programming Language :: Python :: 3.8
Requires-Python: >=3.6
License-File: LICENSE
License-File: AUTHORS.rst
Requires-Dist: Click (>=7.0)
Requires-Dist: PyQt5 (>=5.15.7)
